faiss_gpu-1.7.1.post3.dist-info/LICENSE
faiss_gpu-1.7.1.post3.dist-info/top_level.txt
faiss_gpu-1.7.1.post3.dist-info/RECORD
faiss_gpu-1.7.1.post3.dist-info/WHEEL
faiss_gpu-1.7.1.post3.dist-info/METADATA
faiss_gpu.libs/libgomp-a34b3233.so.1.0.0
faiss_gpu.libs/libgfortran-040039e1.so.5.0.0
faiss_gpu.libs/libquadmath-96973f99.so.0.0.0
faiss_gpu.libs/libz-745e0a09.so.1.2.7
faiss/swigfaiss.py
faiss/__init__.py
faiss/_swigfaiss.cpython-37m-x86_64-linux-gnu.so
faiss/setup.py
faiss/python_callbacks.h
faiss/loader.py
faiss/swigfaiss.i
faiss/contrib/datasets.py
faiss/contrib/__init__.py
faiss/contrib/exhaustive_search.py
faiss/contrib/torch_utils.py
faiss/contrib/vecs_io.py
faiss/contrib/client_server.py
faiss/contrib/ivf_tools.py
faiss/contrib/evaluation.py
faiss/contrib/ondisk.py
faiss/contrib/inspect_tools.py
faiss/contrib/factory_tools.py
faiss/contrib/rpc.py
